mesh_mcp_server/__init__.py
mesh_mcp_server/server.py
mseep_mesh_mcp_server-0.1.4.dist-info/METADATA
mseep_mesh_mcp_server-0.1.4.dist-info/WHEEL
mseep_mesh_mcp_server-0.1.4.dist-info/entry_points.txt
mseep_mesh_mcp_server-0.1.4.dist-info/licenses/LICENSE.md
mseep_mesh_mcp_server-0.1.4.dist-info/RECORD
