Metadata-Version: 2.4
Name: mseep-mesh-mcp-server
Version: 0.1.4
Summary: MCP server for accessing mesh agents through Claude
Author-email: mseep <support@skydeck.ai>
Maintainer-email: Heurist AI <team@heurist.xyz>
License: MIT
License-File: LICENSE.md
Keywords: agents,automation,llm,mcp,mesh
Classifier: Development Status :: 4 - Beta
Classifier: Intended Audience :: Developers
Classifier: License :: OSI Approved :: MIT License
Classifier: Programming Language :: Python :: 3
Classifier: Programming Language :: Python :: 3.10
Requires-Python: >=3.10
Requires-Dist: aiohttp>=3.9.0
Requires-Dist: anyio>=4.5
Requires-Dist: click>=8.1.0
Requires-Dist: colorlog>=6.7.0
Requires-Dist: fastapi>=0.104.0
Requires-Dist: httpx>=0.27
Requires-Dist: mcp
Requires-Dist: pydantic>=2.0.0
Requires-Dist: python-dotenv>=1.0.0
Requires-Dist: requests>=2.28.0
Requires-Dist: uvicorn>=0.24.0
